vapoursynth.pyd
vapoursynth-72.data/data/Lib/site-packages/vapoursynth.dll
vapoursynth-72.dist-info/licenses/COPYING.LESSER
vapoursynth-72.dist-info/METADATA
vapoursynth-72.dist-info/WHEEL
vapoursynth-72.dist-info/top_level.txt
vapoursynth-72.dist-info/RECORD
